<annotation>
	<folder>all</folder>
	<filename>128.jpg</filename>
	<path>C:\invernadero1\modelos\research\object_detection\images\all\128.jpg</path>
	<source>
		<database>Unknown</database>
	</source>
	<size>
		<width>720</width>
		<height>1280</height>
		<depth>3</depth>
	</size>
	<segmented>0</segmented>
	<object>
		<name>tomateRojo</name>
		<pose>Unspecified</pose>
		<truncated>0</truncated>
		<difficult>0</difficult>
		<bndbox>
			<xmin>144</xmin>
			<ymin>799</ymin>
			<xmax>366</xmax>
			<ymax>1029</ymax>
		</bndbox>
	</object>
	<object>
		<name>tomateRojo</name>
		<pose>Unspecified</pose>
		<truncated>0</truncated>
		<difficult>0</difficult>
		<bndbox>
			<xmin>369</xmin>
			<ymin>871</ymin>
			<xmax>557</xmax>
			<ymax>1122</ymax>
		</bndbox>
	</object>
	<object>
		<name>tomateRojo</name>
		<pose>Unspecified</pose>
		<truncated>0</truncated>
		<difficult>0</difficult>
		<bndbox>
			<xmin>340</xmin>
			<ymin>617</ymin>
			<xmax>572</xmax>
			<ymax>837</ymax>
		</bndbox>
	</object>
	<object>
		<name>tomateRojo</name>
		<pose>Unspecified</pose>
		<truncated>0</truncated>
		<difficult>0</difficult>
		<bndbox>
			<xmin>97</xmin>
			<ymin>385</ymin>
			<xmax>304</xmax>
			<ymax>640</ymax>
		</bndbox>
	</object>
	<object>
		<name>tomateRojo</name>
		<pose>Unspecified</pose>
		<truncated>0</truncated>
		<difficult>0</difficult>
		<bndbox>
			<xmin>321</xmin>
			<ymin>274</ymin>
			<xmax>509</xmax>
			<ymax>555</ymax>
		</bndbox>
	</object>
</annotation>
