<annotation>
	<folder>all</folder>
	<filename>242.jpg</filename>
	<path>C:\invernadero1\modelos\research\object_detection\images\all\242.jpg</path>
	<source>
		<database>Unknown</database>
	</source>
	<size>
		<width>720</width>
		<height>1280</height>
		<depth>3</depth>
	</size>
	<segmented>0</segmented>
	<object>
		<name>tomateRojo</name>
		<pose>Unspecified</pose>
		<truncated>0</truncated>
		<difficult>0</difficult>
		<bndbox>
			<xmin>126</xmin>
			<ymin>157</ymin>
			<xmax>351</xmax>
			<ymax>537</ymax>
		</bndbox>
	</object>
	<object>
		<name>tomateRojo</name>
		<pose>Unspecified</pose>
		<truncated>0</truncated>
		<difficult>0</difficult>
		<bndbox>
			<xmin>377</xmin>
			<ymin>205</ymin>
			<xmax>560</xmax>
			<ymax>634</ymax>
		</bndbox>
	</object>
	<object>
		<name>tomateRojo</name>
		<pose>Unspecified</pose>
		<truncated>0</truncated>
		<difficult>0</difficult>
		<bndbox>
			<xmin>332</xmin>
			<ymin>723</ymin>
			<xmax>511</xmax>
			<ymax>1048</ymax>
		</bndbox>
	</object>
	<object>
		<name>tomateRojo</name>
		<pose>Unspecified</pose>
		<truncated>0</truncated>
		<difficult>0</difficult>
		<bndbox>
			<xmin>92</xmin>
			<ymin>699</ymin>
			<xmax>300</xmax>
			<ymax>1092</ymax>
		</bndbox>
	</object>
</annotation>
