<annotation>
	<folder>all</folder>
	<filename>511.jpg</filename>
	<path>C:\invernadero1\modelos\research\object_detection\images\all\511.jpg</path>
	<source>
		<database>Unknown</database>
	</source>
	<size>
		<width>720</width>
		<height>1280</height>
		<depth>3</depth>
	</size>
	<segmented>0</segmented>
	<object>
		<name>tomateVerde</name>
		<pose>Unspecified</pose>
		<truncated>0</truncated>
		<difficult>0</difficult>
		<bndbox>
			<xmin>114</xmin>
			<ymin>777</ymin>
			<xmax>404</xmax>
			<ymax>1129</ymax>
		</bndbox>
	</object>
	<object>
		<name>tomateVerde</name>
		<pose>Unspecified</pose>
		<truncated>0</truncated>
		<difficult>0</difficult>
		<bndbox>
			<xmin>377</xmin>
			<ymin>523</ymin>
			<xmax>571</xmax>
			<ymax>809</ymax>
		</bndbox>
	</object>
	<object>
		<name>tomateVerde</name>
		<pose>Unspecified</pose>
		<truncated>0</truncated>
		<difficult>0</difficult>
		<bndbox>
			<xmin>52</xmin>
			<ymin>497</ymin>
			<xmax>289</xmax>
			<ymax>792</ymax>
		</bndbox>
	</object>
	<object>
		<name>tomateVerde</name>
		<pose>Unspecified</pose>
		<truncated>0</truncated>
		<difficult>0</difficult>
		<bndbox>
			<xmin>237</xmin>
			<ymin>229</ymin>
			<xmax>486</xmax>
			<ymax>528</ymax>
		</bndbox>
	</object>
</annotation>
