<annotation>
	<folder>all</folder>
	<filename>592.jpg</filename>
	<path>C:\invernadero1\modelos\research\object_detection\images\all\592.jpg</path>
	<source>
		<database>Unknown</database>
	</source>
	<size>
		<width>720</width>
		<height>1280</height>
		<depth>3</depth>
	</size>
	<segmented>0</segmented>
	<object>
		<name>tomateVerde</name>
		<pose>Unspecified</pose>
		<truncated>0</truncated>
		<difficult>0</difficult>
		<bndbox>
			<xmin>389</xmin>
			<ymin>840</ymin>
			<xmax>617</xmax>
			<ymax>1152</ymax>
		</bndbox>
	</object>
	<object>
		<name>tomateVerde</name>
		<pose>Unspecified</pose>
		<truncated>0</truncated>
		<difficult>0</difficult>
		<bndbox>
			<xmin>106</xmin>
			<ymin>766</ymin>
			<xmax>311</xmax>
			<ymax>1060</ymax>
		</bndbox>
	</object>
	<object>
		<name>tomateVerde</name>
		<pose>Unspecified</pose>
		<truncated>0</truncated>
		<difficult>0</difficult>
		<bndbox>
			<xmin>323</xmin>
			<ymin>465</ymin>
			<xmax>575</xmax>
			<ymax>748</ymax>
		</bndbox>
	</object>
	<object>
		<name>tomateVerde</name>
		<pose>Unspecified</pose>
		<truncated>0</truncated>
		<difficult>0</difficult>
		<bndbox>
			<xmin>34</xmin>
			<ymin>391</ymin>
			<xmax>300</xmax>
			<ymax>708</ymax>
		</bndbox>
	</object>
	<object>
		<name>tomateVerde</name>
		<pose>Unspecified</pose>
		<truncated>0</truncated>
		<difficult>0</difficult>
		<bndbox>
			<xmin>226</xmin>
			<ymin>191</ymin>
			<xmax>437</xmax>
			<ymax>463</ymax>
		</bndbox>
	</object>
</annotation>
