<annotation>
	<folder>Nueva carpeta (2)</folder>
	<filename>intruso142.jpg</filename>
	<path>C:\Users\acer\Pictures\unsa\Nueva carpeta (2)\intruso142.jpg</path>
	<source>
		<database>Unknown</database>
	</source>
	<size>
		<width>720</width>
		<height>1280</height>
		<depth>3</depth>
	</size>
	<segmented>0</segmented>
	<object>
		<name>intruso</name>
		<pose>Unspecified</pose>
		<truncated>0</truncated>
		<difficult>0</difficult>
		<bndbox>
			<xmin>104</xmin>
			<ymin>235</ymin>
			<xmax>331</xmax>
			<ymax>494</ymax>
		</bndbox>
	</object>
	<object>
		<name>intruso</name>
		<pose>Unspecified</pose>
		<truncated>0</truncated>
		<difficult>0</difficult>
		<bndbox>
			<xmin>383</xmin>
			<ymin>285</ymin>
			<xmax>594</xmax>
			<ymax>566</ymax>
		</bndbox>
	</object>
	<object>
		<name>intruso</name>
		<pose>Unspecified</pose>
		<truncated>0</truncated>
		<difficult>0</difficult>
		<bndbox>
			<xmin>132</xmin>
			<ymin>465</ymin>
			<xmax>408</xmax>
			<ymax>783</ymax>
		</bndbox>
	</object>
	<object>
		<name>intruso</name>
		<pose>Unspecified</pose>
		<truncated>0</truncated>
		<difficult>0</difficult>
		<bndbox>
			<xmin>395</xmin>
			<ymin>643</ymin>
			<xmax>604</xmax>
			<ymax>1039</ymax>
		</bndbox>
	</object>
	<object>
		<name>intruso</name>
		<pose>Unspecified</pose>
		<truncated>0</truncated>
		<difficult>0</difficult>
		<bndbox>
			<xmin>141</xmin>
			<ymin>822</ymin>
			<xmax>371</xmax>
			<ymax>1106</ymax>
		</bndbox>
	</object>
</annotation>
