<annotation>
	<folder>Nueva carpeta (2)</folder>
	<filename>intruso107.jpg</filename>
	<path>C:\Users\acer\Pictures\unsa\Nueva carpeta (2)\intruso107.jpg</path>
	<source>
		<database>Unknown</database>
	</source>
	<size>
		<width>720</width>
		<height>1280</height>
		<depth>3</depth>
	</size>
	<segmented>0</segmented>
	<object>
		<name>intruso</name>
		<pose>Unspecified</pose>
		<truncated>0</truncated>
		<difficult>0</difficult>
		<bndbox>
			<xmin>220</xmin>
			<ymin>128</ymin>
			<xmax>520</xmax>
			<ymax>432</ymax>
		</bndbox>
	</object>
	<object>
		<name>intruso</name>
		<pose>Unspecified</pose>
		<truncated>0</truncated>
		<difficult>0</difficult>
		<bndbox>
			<xmin>43</xmin>
			<ymin>349</ymin>
			<xmax>238</xmax>
			<ymax>685</ymax>
		</bndbox>
	</object>
	<object>
		<name>intruso</name>
		<pose>Unspecified</pose>
		<truncated>0</truncated>
		<difficult>0</difficult>
		<bndbox>
			<xmin>311</xmin>
			<ymin>445</ymin>
			<xmax>566</xmax>
			<ymax>748</ymax>
		</bndbox>
	</object>
	<object>
		<name>intruso</name>
		<pose>Unspecified</pose>
		<truncated>0</truncated>
		<difficult>0</difficult>
		<bndbox>
			<xmin>97</xmin>
			<ymin>777</ymin>
			<xmax>383</xmax>
			<ymax>1086</ymax>
		</bndbox>
	</object>
	<object>
		<name>intruso</name>
		<pose>Unspecified</pose>
		<truncated>0</truncated>
		<difficult>0</difficult>
		<bndbox>
			<xmin>380</xmin>
			<ymin>745</ymin>
			<xmax>604</xmax>
			<ymax>986</ymax>
		</bndbox>
	</object>
</annotation>
